sdxclient/__init__.py
sdxclient/_version.py
sdxclient/client.py
sdxclient/config.py
sdxclient/fablib_token.py
sdxclient/http.py
sdxclient/selection_utils.py
sdxclient/validator.py
sdxclient-0.10.5.dist-info/METADATA
sdxclient-0.10.5.dist-info/WHEEL
sdxclient-0.10.5.dist-info/top_level.txt
sdxclient-0.10.5.dist-info/RECORD
