Metadata-Version: 2.4
Name: sdxclient
Version: 0.10.5
Summary: A Python client library for interacting with the AtlanticWave-SDX L2VPN API
Author-email: FIU <lmarinve@gmail.com>
License: MIT
Project-URL: Homepage, https://github.com/atlanticwave-sdx/sdx-fabric
Project-URL: Issues, https://github.com/atlanticwave-sdx/sdx-fabric/issues
Requires-Python: >=3.9
Requires-Dist: requests>=2.32.5
Requires-Dist: pandas==2.3.3
Requires-Dist: PyJWT==2.9.0
Provides-Extra: fabric
Requires-Dist: fabrictestbed-extensions>=1.5.0; extra == "fabric"
